{
  "book": {
    "number": "2",
    "filenamePrefix": "exodus",
    "bookPage": "exodus.html",
    "title": "Exodus",
    "chapterCount": "40",
    "testament": "old",
    "nt": "false",
    "ot": "true",
    "nextBook": "leviticus_1.html",
    "nextTitle": "Leviticus",
    "prevBook": "genesis_1.html",
    "prevTitle": "Genesis",
    "interlinear": false
  },
  "chapter": {
    "number": "31",
    "verseCount": "18",
    "nextChapter": "exodus_32.html",
    "nextTitle": "Exodus 32",
    "prevChapter": "exodus_30.html",
    "prevTitle": "Exodus 30",
    "filename": "exodus_31.html",
    "keywords": "online king james holy bible, king james bible, bible todo list, words of Jesus, bible index, the authorised version, KJV, KJB, KJAV, AV"
  },
  "items": [
    {
      "type": "verse",
      "id": "v1",
      "number": "1",
      "absolute": "2422",
      "text": "And the <span class='nog'>LORD</span> spake unto Moses, saying,",
      "plainText": "And the LORD spake unto Moses, saying,"
    },
    {
      "type": "verse",
      "id": "v2",
      "number": "2",
      "absolute": "2423",
      "text": "See, I have called by name Bezaleel the son of Uri, the son of Hur, of the tribe of Judah:",
      "plainText": "See, I have called by name Bezaleel the son of Uri, the son of Hur, of the tribe of Judah:"
    },
    {
      "type": "verse",
      "id": "v3",
      "number": "3",
      "absolute": "2424",
      "text": "And I have filled him with the spirit of God, in wisdom, and in understanding, and in knowledge, and in all manner of workmanship,",
      "plainText": "And I have filled him with the spirit of God, in wisdom, and in understanding, and in knowledge, and in all manner of workmanship,"
    },
    {
      "type": "verse",
      "id": "v4",
      "number": "4",
      "absolute": "2425",
      "text": "To devise cunning works, to work in gold, and in silver, and in brass,",
      "plainText": "To devise cunning works, to work in gold, and in silver, and in brass,"
    },
    {
      "type": "verse",
      "id": "v5",
      "number": "5",
      "absolute": "2426",
      "text": "And in cutting of stones, to set <span class='extra'>them</span>, and in carving of timber, to work in all manner of workmanship.",
      "plainText": "And in cutting of stones, to set them, and in carving of timber, to work in all manner of workmanship."
    },
    {
      "type": "verse",
      "id": "v6",
      "number": "6",
      "absolute": "2427",
      "text": "And I, behold, I have given with him Aholiab, the son of Ahisamach, of the tribe of Dan: and in the hearts of all that are wise hearted I have put wisdom, that they may make all that I have commanded thee;",
      "plainText": "And I, behold, I have given with him Aholiab, the son of Ahisamach, of the tribe of Dan: and in the hearts of all that are wise hearted I have put wisdom, that they may make all that I have commanded thee;"
    },
    {
      "type": "verse",
      "id": "v7",
      "number": "7",
      "absolute": "2428",
      "text": "The tabernacle of the congregation, and the ark of the testimony, and the mercy seat that <span class='extra'>is</span> thereupon, and all the furniture of the tabernacle,",
      "plainText": "The tabernacle of the congregation, and the ark of the testimony, and the mercy seat that is thereupon, and all the furniture of the tabernacle,"
    },
    {
      "type": "verse",
      "id": "v8",
      "number": "8",
      "absolute": "2429",
      "text": "And the table and his furniture, and the pure candlestick with all his furniture, and the altar of incense,",
      "plainText": "And the table and his furniture, and the pure candlestick with all his furniture, and the altar of incense,"
    },
    {
      "type": "verse",
      "id": "v9",
      "number": "9",
      "absolute": "2430",
      "text": "And the altar of burnt offering with all his furniture, and the laver and his foot,",
      "plainText": "And the altar of burnt offering with all his furniture, and the laver and his foot,"
    },
    {
      "type": "verse",
      "id": "v10",
      "number": "10",
      "absolute": "2431",
      "text": "And the cloths of service, and the holy garments for Aaron the priest, and the garments of his sons, to minister in the priest's office,",
      "plainText": "And the cloths of service, and the holy garments for Aaron the priest, and the garments of his sons, to minister in the priest's office,"
    },
    {
      "type": "verse",
      "id": "v11",
      "number": "11",
      "absolute": "2432",
      "text": "And the anointing oil, and sweet incense for the holy <span class='extra'>place</span>: according to all that I have commanded thee shall they do.",
      "plainText": "And the anointing oil, and sweet incense for the holy place: according to all that I have commanded thee shall they do."
    },
    {
      "type": "verse",
      "id": "v12",
      "number": "12",
      "absolute": "2433",
      "text": "And the <span class='nog'>LORD</span> spake unto Moses, saying,",
      "plainText": "And the LORD spake unto Moses, saying,"
    },
    {
      "type": "verse",
      "id": "v13",
      "number": "13",
      "absolute": "2434",
      "text": "Speak thou also unto the children of Israel, saying, Verily my sabbaths ye shall keep: for it <span class='extra'>is</span> a sign between me and you throughout your generations; that <span class='extra'>ye</span> may know that I <span class='extra'>am</span> the <span class='nog'>LORD</span> that doth sanctify you.",
      "plainText": "Speak thou also unto the children of Israel, saying, Verily my sabbaths ye shall keep: for it is a sign between me and you throughout your generations; that ye may know that I am the LORD that doth sanctify you."
    },
    {
      "type": "verse",
      "id": "v14",
      "number": "14",
      "absolute": "2435",
      "text": "Ye shall keep the sabbath therefore; for it <span class='extra'>is</span> holy unto you: every one that defileth it shall surely be put to death: for whosoever doeth <span class='extra'>any</span> work therein, that soul shall be cut off from among his people.",
      "plainText": "Ye shall keep the sabbath therefore; for it is holy unto you: every one that defileth it shall surely be put to death: for whosoever doeth any work therein, that soul shall be cut off from among his people."
    },
    {
      "type": "verse",
      "id": "v15",
      "number": "15",
      "absolute": "2436",
      "text": "Six days may work be done; but in the seventh <span class='extra'>is</span> the sabbath of rest, holy to the <span class='nog'>LORD</span>: whosoever doeth <span class='extra'>any</span> work in the sabbath day, he shall surely be put to death.",
      "plainText": "Six days may work be done; but in the seventh is the sabbath of rest, holy to the LORD: whosoever doeth any work in the sabbath day, he shall surely be put to death."
    },
    {
      "type": "verse",
      "id": "v16",
      "number": "16",
      "absolute": "2437",
      "text": "Wherefore the children of Israel shall keep the sabbath, to observe the sabbath throughout their generations, <span class='extra'>for</span> a perpetual covenant.",
      "plainText": "Wherefore the children of Israel shall keep the sabbath, to observe the sabbath throughout their generations, for a perpetual covenant."
    },
    {
      "type": "verse",
      "id": "v17",
      "number": "17",
      "absolute": "2438",
      "text": "It <span class='extra'>is</span> a sign between me and the children of Israel for ever: for <span class='extra'>in</span> six days the <span class='nog'>LORD</span> made heaven and earth, and on the seventh day he rested, and was refreshed.",
      "plainText": "It is a sign between me and the children of Israel for ever: for in six days the LORD made heaven and earth, and on the seventh day he rested, and was refreshed."
    },
    {
      "type": "verse",
      "id": "v18",
      "number": "18",
      "absolute": "2439",
      "text": "And he gave unto Moses, when he had made an end of communing with him upon mount Sinai, two tables of testimony, tables of stone, written with the finger of God.",
      "plainText": "And he gave unto Moses, when he had made an end of communing with him upon mount Sinai, two tables of testimony, tables of stone, written with the finger of God."
    }
  ]
}