{
  "book": {
    "number" : "1",
    "filenamePrefix" : "genesis",
    "bookPage" : "genesis.html",
    "title" : "Genesis",
    "chapterCount" : "50",
    "testament" : "old",
    "nt" : "false",
    "ot" : "true",
    "nextBook" : "exodus_1.html",
    "nextTitle" : "Exodus",
    "prevBook" : "revelation_1.html",
    "prevTitle" : "Revelation"
  },
  "chapter": {
    "number" : "46",
    "verseCount" : "34",
    "nextChapter" : "genesis_47.html",
    "nextTitle" : "Genesis 47",
    "prevChapter" : "genesis_45.html",
    "prevTitle" : "Genesis 45",
    "filename" : "genesis_46.html",
    "keywords" : "online king james holy bible, king james bible, bible todo list, words of Jesus, bible index, the authorised version, KJV, KJB, KJAV, AV"
  },
  "items": [
    {
      "type" : "verse",
      "id" : "v1",
      "number" : "1",
      "absolute" : "1388",
      "text" : "And Israel took his journey with all that he had, and came to Beer-sheba, and offered sacrifices unto the God of his father Isaac.",
      "plainText" : "And Israel took his journey with all that he had, and came to Beer-sheba, and offered sacrifices unto the God of his father Isaac."
    }
    ,
    {
      "type" : "verse",
      "id" : "v2",
      "number" : "2",
      "absolute" : "1389",
      "text" : "And God spake unto Israel in the visions of the night, and said, Jacob, Jacob. And he said, Here <span class='extra'>am<\/span> I.",
      "plainText" : "And God spake unto Israel in the visions of the night, and said, Jacob, Jacob. And he said, Here am I."
    }
    ,
    {
      "type" : "verse",
      "id" : "v3",
      "number" : "3",
      "absolute" : "1390",
      "text" : "And he said, I <span class='extra'>am<\/span> God, the God of thy father: fear not to go down into Egypt; for I will there make of thee a great nation:",
      "plainText" : "And he said, I am God, the God of thy father: fear not to go down into Egypt; for I will there make of thee a great nation:"
    }
    ,
    {
      "type" : "verse",
      "id" : "v4",
      "number" : "4",
      "absolute" : "1391",
      "text" : "I will go down with thee into Egypt; and I will also surely bring thee up <span class='extra'>again<\/span>: and Joseph shall put his hand upon thine eyes.",
      "plainText" : "I will go down with thee into Egypt; and I will also surely bring thee up again: and Joseph shall put his hand upon thine eyes."
    }
    ,
    {
      "type" : "verse",
      "id" : "v5",
      "number" : "5",
      "absolute" : "1392",
      "text" : "And Jacob rose up from Beer-sheba: and the sons of Israel carried Jacob their father, and their little ones, and their wives, in the wagons which Pharaoh had sent to carry him.",
      "plainText" : "And Jacob rose up from Beer-sheba: and the sons of Israel carried Jacob their father, and their little ones, and their wives, in the wagons which Pharaoh had sent to carry him."
    }
    ,
    {
      "type" : "verse",
      "id" : "v6",
      "number" : "6",
      "absolute" : "1393",
      "text" : "And they took their cattle, and their goods, which they had gotten in the land of Canaan, and came into Egypt, Jacob, and all his seed with him:",
      "plainText" : "And they took their cattle, and their goods, which they had gotten in the land of Canaan, and came into Egypt, Jacob, and all his seed with him:"
    }
    ,
    {
      "type" : "verse",
      "id" : "v7",
      "number" : "7",
      "absolute" : "1394",
      "text" : "His sons, and his sons' sons with him, his daughters, and his sons' daughters, and all his seed brought he with him into Egypt.",
      "plainText" : "His sons, and his sons' sons with him, his daughters, and his sons' daughters, and all his seed brought he with him into Egypt."
    }
    ,
    {
      "type" : "verse",
      "id" : "v8",
      "number" : "8",
      "absolute" : "1395",
      "text" : "And these <span class='extra'>are<\/span> the names of the children of Israel, which came into Egypt, Jacob and his sons: Reuben, Jacob's firstborn.",
      "plainText" : "And these are the names of the children of Israel, which came into Egypt, Jacob and his sons: Reuben, Jacob's firstborn."
    }
    ,
    {
      "type" : "verse",
      "id" : "v9",
      "number" : "9",
      "absolute" : "1396",
      "text" : "And the sons of Reuben; Hanoch, and Phallu, and Hezron, and Carmi.",
      "plainText" : "And the sons of Reuben; Hanoch, and Phallu, and Hezron, and Carmi."
    }
    ,
    {
      "type" : "verse",
      "id" : "v10",
      "number" : "10",
      "absolute" : "1397",
      "text" : "And the sons of Simeon; Jemuel, and Jamin, and Ohad, and Jachin, and Zohar, and Shaul the son of a Canaanitish woman.",
      "plainText" : "And the sons of Simeon; Jemuel, and Jamin, and Ohad, and Jachin, and Zohar, and Shaul the son of a Canaanitish woman."
    }
    ,
    {
      "type" : "verse",
      "id" : "v11",
      "number" : "11",
      "absolute" : "1398",
      "text" : "And the sons of Levi; Gershon, Kohath, and Merari.",
      "plainText" : "And the sons of Levi; Gershon, Kohath, and Merari."
    }
    ,
    {
      "type" : "verse",
      "id" : "v12",
      "number" : "12",
      "absolute" : "1399",
      "text" : "And the sons of Judah; Er, and Onan, and Shelah, and Pharez, and Zerah: but Er and Onan died in the land of Canaan. And the sons of Pharez were Hezron and Hamul.",
      "plainText" : "And the sons of Judah; Er, and Onan, and Shelah, and Pharez, and Zerah: but Er and Onan died in the land of Canaan. And the sons of Pharez were Hezron and Hamul."
    }
    ,
    {
      "type" : "verse",
      "id" : "v13",
      "number" : "13",
      "absolute" : "1400",
      "text" : "And the sons of Issachar; Tola, and Phuvah, and Job, and Shimron.",
      "plainText" : "And the sons of Issachar; Tola, and Phuvah, and Job, and Shimron."
    }
    ,
    {
      "type" : "verse",
      "id" : "v14",
      "number" : "14",
      "absolute" : "1401",
      "text" : "And the sons of Zebulun; Sered, and Elon, and Jahleel.",
      "plainText" : "And the sons of Zebulun; Sered, and Elon, and Jahleel."
    }
    ,
    {
      "type" : "verse",
      "id" : "v15",
      "number" : "15",
      "absolute" : "1402",
      "text" : "These <span class='extra'>be<\/span> the sons of Leah, which she bare unto Jacob in Padan-aram, with his daughter Dinah: all the souls of his sons and his daughters <span class='extra'>were<\/span> thirty and three.",
      "plainText" : "These be the sons of Leah, which she bare unto Jacob in Padan-aram, with his daughter Dinah: all the souls of his sons and his daughters were thirty and three."
    }
    ,
    {
      "type" : "verse",
      "id" : "v16",
      "number" : "16",
      "absolute" : "1403",
      "text" : "And the sons of Gad; Ziphion, and Haggi, Shuni, and Ezbon, Eri, and Arodi, and Areli.",
      "plainText" : "And the sons of Gad; Ziphion, and Haggi, Shuni, and Ezbon, Eri, and Arodi, and Areli."
    }
    ,
    {
      "type" : "verse",
      "id" : "v17",
      "number" : "17",
      "absolute" : "1404",
      "text" : "And the sons of Asher; Jimnah, and Ishuah, and Isui, and Beriah, and Serah their sister: and the sons of Beriah; Heber, and Malchiel.",
      "plainText" : "And the sons of Asher; Jimnah, and Ishuah, and Isui, and Beriah, and Serah their sister: and the sons of Beriah; Heber, and Malchiel."
    }
    ,
    {
      "type" : "verse",
      "id" : "v18",
      "number" : "18",
      "absolute" : "1405",
      "text" : "These <span class='extra'>are<\/span> the sons of Zilpah, whom Laban gave to Leah his daughter, and these she bare unto Jacob, <span class='extra'>even<\/span> sixteen souls.",
      "plainText" : "These are the sons of Zilpah, whom Laban gave to Leah his daughter, and these she bare unto Jacob, even sixteen souls."
    }
    ,
    {
      "type" : "verse",
      "id" : "v19",
      "number" : "19",
      "absolute" : "1406",
      "text" : "The sons of Rachel Jacob's wife; Joseph, and Benjamin.",
      "plainText" : "The sons of Rachel Jacob's wife; Joseph, and Benjamin."
    }
    ,
    {
      "type" : "verse",
      "id" : "v20",
      "number" : "20",
      "absolute" : "1407",
      "text" : "And unto Joseph in the land of Egypt were born Manasseh and Ephraim, which Asenath the daughter of Poti-pherah priest of On bare unto him.",
      "plainText" : "And unto Joseph in the land of Egypt were born Manasseh and Ephraim, which Asenath the daughter of Poti-pherah priest of On bare unto him."
    }
    ,
    {
      "type" : "verse",
      "id" : "v21",
      "number" : "21",
      "absolute" : "1408",
      "text" : "And the sons of Benjamin <span class='extra'>were<\/span> Belah, and Becher, and Ashbel, Gera, and Naaman, Ehi, and Rosh, Muppim, and Huppim, and Ard.",
      "plainText" : "And the sons of Benjamin were Belah, and Becher, and Ashbel, Gera, and Naaman, Ehi, and Rosh, Muppim, and Huppim, and Ard."
    }
    ,
    {
      "type" : "verse",
      "id" : "v22",
      "number" : "22",
      "absolute" : "1409",
      "text" : "These <span class='extra'>are<\/span> the sons of Rachel, which were born to Jacob: all the souls <span class='extra'>were<\/span> fourteen.",
      "plainText" : "These are the sons of Rachel, which were born to Jacob: all the souls were fourteen."
    }
    ,
    {
      "type" : "verse",
      "id" : "v23",
      "number" : "23",
      "absolute" : "1410",
      "text" : "And the sons of Dan; Hushim.",
      "plainText" : "And the sons of Dan; Hushim."
    }
    ,
    {
      "type" : "verse",
      "id" : "v24",
      "number" : "24",
      "absolute" : "1411",
      "text" : "And the sons of Naphtali; Jahzeel, and Guni, and Jezer, and Shillem.",
      "plainText" : "And the sons of Naphtali; Jahzeel, and Guni, and Jezer, and Shillem."
    }
    ,
    {
      "type" : "verse",
      "id" : "v25",
      "number" : "25",
      "absolute" : "1412",
      "text" : "These <span class='extra'>are<\/span> the sons of Bilhah, which Laban gave unto Rachel his daughter, and she bare these unto Jacob: all the souls <span class='extra'>were<\/span> seven.",
      "plainText" : "These are the sons of Bilhah, which Laban gave unto Rachel his daughter, and she bare these unto Jacob: all the souls were seven."
    }
    ,
    {
      "type" : "verse",
      "id" : "v26",
      "number" : "26",
      "absolute" : "1413",
      "text" : "All the souls that came with Jacob into Egypt, which came out of his loins, besides Jacob's sons' wives, all the souls <span class='extra'>were<\/span> threescore and six;",
      "plainText" : "All the souls that came with Jacob into Egypt, which came out of his loins, besides Jacob's sons' wives, all the souls were threescore and six;"
    }
    ,
    {
      "type" : "verse",
      "id" : "v27",
      "number" : "27",
      "absolute" : "1414",
      "text" : "And the sons of Joseph, which were born him in Egypt, <span class='extra'>were<\/span> two souls: all the souls of the house of Jacob, which came into Egypt, <span class='extra'>were<\/span> threescore and ten.",
      "plainText" : "And the sons of Joseph, which were born him in Egypt, were two souls: all the souls of the house of Jacob, which came into Egypt, were threescore and ten."
    }
    ,
    {
      "type" : "verse",
      "id" : "v28",
      "number" : "28",
      "absolute" : "1415",
      "text" : "And he sent Judah before him unto Joseph, to direct his face unto Goshen; and they came into the land of Goshen.",
      "plainText" : "And he sent Judah before him unto Joseph, to direct his face unto Goshen; and they came into the land of Goshen."
    }
    ,
    {
      "type" : "verse",
      "id" : "v29",
      "number" : "29",
      "absolute" : "1416",
      "text" : "And Joseph made ready his chariot, and went up to meet Israel his father, to Goshen, and presented himself unto him; and he fell on his neck, and wept on his neck a good while.",
      "plainText" : "And Joseph made ready his chariot, and went up to meet Israel his father, to Goshen, and presented himself unto him; and he fell on his neck, and wept on his neck a good while."
    }
    ,
    {
      "type" : "verse",
      "id" : "v30",
      "number" : "30",
      "absolute" : "1417",
      "text" : "And Israel said unto Joseph, Now let me die, since I have seen thy face, because thou <span class='extra'>art<\/span> yet alive.",
      "plainText" : "And Israel said unto Joseph, Now let me die, since I have seen thy face, because thou art yet alive."
    }
    ,
    {
      "type" : "verse",
      "id" : "v31",
      "number" : "31",
      "absolute" : "1418",
      "text" : "And Joseph said unto his brethren, and unto his father's house, I will go up, and shew Pharaoh, and say unto him, My brethren, and my father's house, which <span class='extra'>were<\/span> in the land of Canaan, are come unto me;",
      "plainText" : "And Joseph said unto his brethren, and unto his father's house, I will go up, and shew Pharaoh, and say unto him, My brethren, and my father's house, which were in the land of Canaan, are come unto me;"
    }
    ,
    {
      "type" : "verse",
      "id" : "v32",
      "number" : "32",
      "absolute" : "1419",
      "text" : "And the men <span class='extra'>are<\/span> shepherds, for their trade hath been to feed cattle; and they have brought their flocks, and their herds, and all that they have.",
      "plainText" : "And the men are shepherds, for their trade hath been to feed cattle; and they have brought their flocks, and their herds, and all that they have."
    }
    ,
    {
      "type" : "verse",
      "id" : "v33",
      "number" : "33",
      "absolute" : "1420",
      "text" : "And it shall come to pass, when Pharaoh shall call you, and shall say, What <span class='extra'>is<\/span> your occupation?",
      "plainText" : "And it shall come to pass, when Pharaoh shall call you, and shall say, What is your occupation?"
    }
    ,
    {
      "type" : "verse",
      "id" : "v34",
      "number" : "34",
      "absolute" : "1421",
      "text" : "That ye shall say, Thy servants' trade hath been about cattle from our youth even until now, both we, <span class='extra'>and<\/span> also our fathers: that ye may dwell in the land of Goshen; for every shepherd <span class='extra'>is<\/span> an abomination unto the Egyptians.",
      "plainText" : "That ye shall say, Thy servants' trade hath been about cattle from our youth even until now, both we, and also our fathers: that ye may dwell in the land of Goshen; for every shepherd is an abomination unto the Egyptians."
    }
  ]
}

