{
  "book": {
    "number" : "24",
    "filenamePrefix" : "jeremiah",
    "bookPage" : "jeremiah.html",
    "title" : "Jeremiah",
    "chapterCount" : "52",
    "testament" : "old",
    "nt" : "false",
    "ot" : "true",
    "nextBook" : "lamentations_1.html",
    "nextTitle" : "Lamentations",
    "prevBook" : "isaiah_1.html",
    "prevTitle" : "Isaiah"
  },
  "chapter": {
    "number" : "18",
    "verseCount" : "23",
    "nextChapter" : "jeremiah_19.html",
    "nextTitle" : "Jeremiah 19",
    "prevChapter" : "jeremiah_17.html",
    "prevTitle" : "Jeremiah 17",
    "filename" : "jeremiah_18.html",
    "keywords" : "online king james holy bible, king james bible, bible todo list, words of Jesus, bible index, the authorised version, KJV, KJB, KJAV, AV"
  },
  "items": [
    {
      "type" : "verse",
      "id" : "v1",
      "number" : "1",
      "absolute" : "19386",
      "text" : "The word which came to Jeremiah from the <span class='nog'>LORD<\/span>, saying,",
      "plainText" : "The word which came to Jeremiah from the LORD, saying,"
    }
    ,
    {
      "type" : "verse",
      "id" : "v2",
      "number" : "2",
      "absolute" : "19387",
      "text" : "Arise, and go down to the potter's house, and there I will cause thee to hear my words.",
      "plainText" : "Arise, and go down to the potter's house, and there I will cause thee to hear my words."
    }
    ,
    {
      "type" : "verse",
      "id" : "v3",
      "number" : "3",
      "absolute" : "19388",
      "text" : "Then I went down to the potter's house, and, behold, he wrought a work on the wheels.",
      "plainText" : "Then I went down to the potter's house, and, behold, he wrought a work on the wheels."
    }
    ,
    {
      "type" : "verse",
      "id" : "v4",
      "number" : "4",
      "absolute" : "19389",
      "text" : "And the vessel that he made of clay was marred in the hand of the potter: so he made it again another vessel, as seemed good to the potter to make <span class='extra'>it<\/span>.",
      "plainText" : "And the vessel that he made of clay was marred in the hand of the potter: so he made it again another vessel, as seemed good to the potter to make it."
    }
    ,
    {
      "type" : "verse",
      "id" : "v5",
      "number" : "5",
      "absolute" : "19390",
      "text" : "Then the word of the <span class='nog'>LORD<\/span> came to me, saying,",
      "plainText" : "Then the word of the LORD came to me, saying,"
    }
    ,
    {
      "type" : "verse",
      "id" : "v6",
      "number" : "6",
      "absolute" : "19391",
      "text" : "O house of Israel, cannot I do with you as this potter? saith the <span class='nog'>LORD<\/span>. Behold, as the clay <span class='extra'>is<\/span> in the potter's hand, so <span class='extra'>are<\/span> ye in mine hand, O house of Israel.",
      "plainText" : "O house of Israel, cannot I do with you as this potter? saith the LORD. Behold, as the clay is in the potter's hand, so are ye in mine hand, O house of Israel."
    }
    ,
    {
      "type" : "verse",
      "id" : "v7",
      "number" : "7",
      "absolute" : "19392",
      "text" : "<span class='extra'>At what<\/span> instant I shall speak concerning a nation, and concerning a kingdom, to pluck up, and to pull down, and to destroy <span class='extra'>it<\/span>;",
      "plainText" : "At what instant I shall speak concerning a nation, and concerning a kingdom, to pluck up, and to pull down, and to destroy it;"
    }
    ,
    {
      "type" : "verse",
      "id" : "v8",
      "number" : "8",
      "absolute" : "19393",
      "text" : "If that nation, against whom I have pronounced, turn from their evil, I will repent of the evil that I thought to do unto them.",
      "plainText" : "If that nation, against whom I have pronounced, turn from their evil, I will repent of the evil that I thought to do unto them."
    }
    ,
    {
      "type" : "verse",
      "id" : "v9",
      "number" : "9",
      "absolute" : "19394",
      "text" : "And <span class='extra'>at what<\/span> instant I shall speak concerning a nation, and concerning a kingdom, to build and to plant <span class='extra'>it<\/span>;",
      "plainText" : "And at what instant I shall speak concerning a nation, and concerning a kingdom, to build and to plant it;"
    }
    ,
    {
      "type" : "verse",
      "id" : "v10",
      "number" : "10",
      "absolute" : "19395",
      "text" : "If it do evil in my sight, that it obey not my voice, then I will repent of the good, wherewith I said I would benefit them.",
      "plainText" : "If it do evil in my sight, that it obey not my voice, then I will repent of the good, wherewith I said I would benefit them."
    }
    ,
    {
      "type" : "verse",
      "id" : "v11",
      "number" : "11",
      "absolute" : "19396",
      "text" : "Now therefore go to, speak to the men of Judah, and to the inhabitants of Jerusalem, saying, Thus saith the <span class='nog'>LORD<\/span>; Behold, I frame evil against you, and devise a device against you: return ye now every one from his evil way, and make your ways and your doings good.",
      "plainText" : "Now therefore go to, speak to the men of Judah, and to the inhabitants of Jerusalem, saying, Thus saith the LORD; Behold, I frame evil against you, and devise a device against you: return ye now every one from his evil way, and make your ways and your doings good."
    }
    ,
    {
      "type" : "verse",
      "id" : "v12",
      "number" : "12",
      "absolute" : "19397",
      "text" : "And they said, There is no hope: but we will walk after our own devices, and we will every one do the imagination of his evil heart.",
      "plainText" : "And they said, There is no hope: but we will walk after our own devices, and we will every one do the imagination of his evil heart."
    }
    ,
    {
      "type" : "verse",
      "id" : "v13",
      "number" : "13",
      "absolute" : "19398",
      "text" : "Therefore thus saith the <span class='nog'>LORD<\/span>; Ask ye now among the heathen, who hath heard such things: the virgin of Israel hath done a very horrible thing.",
      "plainText" : "Therefore thus saith the LORD; Ask ye now among the heathen, who hath heard such things: the virgin of Israel hath done a very horrible thing."
    }
    ,
    {
      "type" : "verse",
      "id" : "v14",
      "number" : "14",
      "absolute" : "19399",
      "text" : "Will <span class='extra'>a man<\/span> leave the snow of Lebanon <span class='extra'>which cometh<\/span> from the rock of the field? <span class='extra'>or<\/span> shall the cold flowing waters that come from another place be forsaken?",
      "plainText" : "Will a man leave the snow of Lebanon which cometh from the rock of the field? or shall the cold flowing waters that come from another place be forsaken?"
    }
    ,
    {
      "type" : "verse",
      "id" : "v15",
      "number" : "15",
      "absolute" : "19400",
      "text" : "Because my people hath forgotten me, they have burned incense to vanity, and they have caused them to stumble in their ways <span class='extra'>from<\/span> the ancient paths, to walk in paths, <span class='extra'>in<\/span> a way not cast up;",
      "plainText" : "Because my people hath forgotten me, they have burned incense to vanity, and they have caused them to stumble in their ways from the ancient paths, to walk in paths, in a way not cast up;"
    }
    ,
    {
      "type" : "verse",
      "id" : "v16",
      "number" : "16",
      "absolute" : "19401",
      "text" : "To make their land desolate, <span class='extra'>and<\/span> a perpetual hissing; every one that passeth thereby shall be astonished, and wag his head.",
      "plainText" : "To make their land desolate, and a perpetual hissing; every one that passeth thereby shall be astonished, and wag his head."
    }
    ,
    {
      "type" : "verse",
      "id" : "v17",
      "number" : "17",
      "absolute" : "19402",
      "text" : "I will scatter them as with an east wind before the enemy; I will shew them the back, and not the face, in the day of their calamity.",
      "plainText" : "I will scatter them as with an east wind before the enemy; I will shew them the back, and not the face, in the day of their calamity."
    }
    ,
    {
      "type" : "verse",
      "id" : "v18",
      "number" : "18",
      "absolute" : "19403",
      "text" : "Then said they, Come, and let us devise devices against Jeremiah; for the law shall not perish from the priest, nor counsel from the wise, nor the word from the prophet. Come, and let us smite him with the tongue, and let us not give heed to any of his words.",
      "plainText" : "Then said they, Come, and let us devise devices against Jeremiah; for the law shall not perish from the priest, nor counsel from the wise, nor the word from the prophet. Come, and let us smite him with the tongue, and let us not give heed to any of his words."
    }
    ,
    {
      "type" : "verse",
      "id" : "v19",
      "number" : "19",
      "absolute" : "19404",
      "text" : "Give heed to me, O <span class='nog'>LORD<\/span>, and hearken to the voice of them that contend with me.",
      "plainText" : "Give heed to me, O LORD, and hearken to the voice of them that contend with me."
    }
    ,
    {
      "type" : "verse",
      "id" : "v20",
      "number" : "20",
      "absolute" : "19405",
      "text" : "Shall evil be recompensed for good? for they have digged a pit for my soul. Remember that I stood before thee to speak good for them, <span class='extra'>and<\/span> to turn away thy wrath from them.",
      "plainText" : "Shall evil be recompensed for good? for they have digged a pit for my soul. Remember that I stood before thee to speak good for them, and to turn away thy wrath from them."
    }
    ,
    {
      "type" : "verse",
      "id" : "v21",
      "number" : "21",
      "absolute" : "19406",
      "text" : "Therefore deliver up their children to the famine, and pour out their <span class='extra'>blood<\/span> by the force of the sword; and let their wives be bereaved of their children, and <span class='extra'>be<\/span> widows; and let their men be put to death; <span class='extra'>let<\/span> their young men <span class='extra'>be<\/span> slain by the sword in battle.",
      "plainText" : "Therefore deliver up their children to the famine, and pour out their blood by the force of the sword; and let their wives be bereaved of their children, and be widows; and let their men be put to death; let their young men be slain by the sword in battle."
    }
    ,
    {
      "type" : "verse",
      "id" : "v22",
      "number" : "22",
      "absolute" : "19407",
      "text" : "Let a cry be heard from their houses, when thou shalt bring a troop suddenly upon them: for they have digged a pit to take me, and hid snares for my feet.",
      "plainText" : "Let a cry be heard from their houses, when thou shalt bring a troop suddenly upon them: for they have digged a pit to take me, and hid snares for my feet."
    }
    ,
    {
      "type" : "verse",
      "id" : "v23",
      "number" : "23",
      "absolute" : "19408",
      "text" : "Yet, <span class='nog'>LORD<\/span>, thou knowest all their counsel against me to slay <span class='extra'>me<\/span>: forgive not their iniquity, neither blot out their sin from thy sight, but let them be overthrown before thee; deal <span class='extra'>thus<\/span> with them in the time of thine anger.",
      "plainText" : "Yet, LORD, thou knowest all their counsel against me to slay me: forgive not their iniquity, neither blot out their sin from thy sight, but let them be overthrown before thee; deal thus with them in the time of thine anger."
    }
  ]
}


