{
  "book": {
    "number" : "18",
    "filenamePrefix" : "job",
    "bookPage" : "job.html",
    "title" : "Job",
    "chapterCount" : "42",
    "testament" : "old",
    "nt" : "false",
    "ot" : "true",
    "nextBook" : "psalms_1.html",
    "nextTitle" : "Psalms",
    "prevBook" : "esther_1.html",
    "prevTitle" : "Esther"
  },
  "chapter": {
    "number" : "33",
    "verseCount" : "33",
    "nextChapter" : "job_34.html",
    "nextTitle" : "Job 34",
    "prevChapter" : "job_32.html",
    "prevTitle" : "Job 32",
    "filename" : "job_33.html",
    "keywords" : "online king james holy bible, king james bible, bible todo list, words of Jesus, bible index, the authorised version, KJV, KJB, KJAV, AV"
  },
  "items": [
    {
      "type" : "verse",
      "id" : "v1",
      "number" : "1",
      "absolute" : "13652",
      "text" : "Wherefore, Job, I pray thee, hear my speeches, and hearken to all my words.",
      "plainText" : "Wherefore, Job, I pray thee, hear my speeches, and hearken to all my words."
    }
    ,
    {
      "type" : "verse",
      "id" : "v2",
      "number" : "2",
      "absolute" : "13653",
      "text" : "Behold, now I have opened my mouth, my tongue hath spoken in my mouth.",
      "plainText" : "Behold, now I have opened my mouth, my tongue hath spoken in my mouth."
    }
    ,
    {
      "type" : "verse",
      "id" : "v3",
      "number" : "3",
      "absolute" : "13654",
      "text" : "My words <span class='extra'>shall be of<\/span> the uprightness of my heart: and my lips shall utter knowledge clearly.",
      "plainText" : "My words shall be of the uprightness of my heart: and my lips shall utter knowledge clearly."
    }
    ,
    {
      "type" : "verse",
      "id" : "v4",
      "number" : "4",
      "absolute" : "13655",
      "text" : "The Spirit of God hath made me, and the breath of the Almighty hath given me life.",
      "plainText" : "The Spirit of God hath made me, and the breath of the Almighty hath given me life."
    }
    ,
    {
      "type" : "verse",
      "id" : "v5",
      "number" : "5",
      "absolute" : "13656",
      "text" : "If thou canst answer me, set <span class='extra'>thy words<\/span> in order before me, stand up.",
      "plainText" : "If thou canst answer me, set thy words in order before me, stand up."
    }
    ,
    {
      "type" : "verse",
      "id" : "v6",
      "number" : "6",
      "absolute" : "13657",
      "text" : "Behold, I <span class='extra'>am<\/span> according to thy wish in God's stead: I also am formed out of the clay.",
      "plainText" : "Behold, I am according to thy wish in God's stead: I also am formed out of the clay."
    }
    ,
    {
      "type" : "verse",
      "id" : "v7",
      "number" : "7",
      "absolute" : "13658",
      "text" : "Behold, my terror shall not make thee afraid, neither shall my hand be heavy upon thee.",
      "plainText" : "Behold, my terror shall not make thee afraid, neither shall my hand be heavy upon thee."
    }
    ,
    {
      "type" : "verse",
      "id" : "v8",
      "number" : "8",
      "absolute" : "13659",
      "text" : "Surely thou hast spoken in mine hearing, and I have heard the voice of <span class='extra'>thy<\/span> words, <span class='extra'>saying<\/span>,",
      "plainText" : "Surely thou hast spoken in mine hearing, and I have heard the voice of thy words, saying,"
    }
    ,
    {
      "type" : "verse",
      "id" : "v9",
      "number" : "9",
      "absolute" : "13660",
      "text" : "I am clean without transgression, I <span class='extra'>am<\/span> innocent; neither <span class='extra'>is there<\/span> iniquity in me.",
      "plainText" : "I am clean without transgression, I am innocent; neither is there iniquity in me."
    }
    ,
    {
      "type" : "verse",
      "id" : "v10",
      "number" : "10",
      "absolute" : "13661",
      "text" : "Behold, he findeth occasions against me, he counteth me for his enemy,",
      "plainText" : "Behold, he findeth occasions against me, he counteth me for his enemy,"
    }
    ,
    {
      "type" : "verse",
      "id" : "v11",
      "number" : "11",
      "absolute" : "13662",
      "text" : "He putteth my feet in the stocks, he marketh all my paths.",
      "plainText" : "He putteth my feet in the stocks, he marketh all my paths."
    }
    ,
    {
      "type" : "verse",
      "id" : "v12",
      "number" : "12",
      "absolute" : "13663",
      "text" : "Behold, <span class='extra'>in<\/span> this thou art not just: I will answer thee, that God is greater than man.",
      "plainText" : "Behold, in this thou art not just: I will answer thee, that God is greater than man."
    }
    ,
    {
      "type" : "verse",
      "id" : "v13",
      "number" : "13",
      "absolute" : "13664",
      "text" : "Why dost thou strive against him? for he giveth not account of any of his matters.",
      "plainText" : "Why dost thou strive against him? for he giveth not account of any of his matters."
    }
    ,
    {
      "type" : "verse",
      "id" : "v14",
      "number" : "14",
      "absolute" : "13665",
      "text" : "For God speaketh once, yea twice, <span class='extra'>yet man<\/span> perceiveth it not.",
      "plainText" : "For God speaketh once, yea twice, yet man perceiveth it not."
    }
    ,
    {
      "type" : "verse",
      "id" : "v15",
      "number" : "15",
      "absolute" : "13666",
      "text" : "In a dream, in a vision of the night, when deep sleep falleth upon men, in slumberings upon the bed;",
      "plainText" : "In a dream, in a vision of the night, when deep sleep falleth upon men, in slumberings upon the bed;"
    }
    ,
    {
      "type" : "verse",
      "id" : "v16",
      "number" : "16",
      "absolute" : "13667",
      "text" : "Then he openeth the ears of men, and sealeth their instruction,",
      "plainText" : "Then he openeth the ears of men, and sealeth their instruction,"
    }
    ,
    {
      "type" : "verse",
      "id" : "v17",
      "number" : "17",
      "absolute" : "13668",
      "text" : "That he may withdraw man <span class='extra'>from his<\/span> purpose, and hide pride from man.",
      "plainText" : "That he may withdraw man from his purpose, and hide pride from man."
    }
    ,
    {
      "type" : "verse",
      "id" : "v18",
      "number" : "18",
      "absolute" : "13669",
      "text" : "He keepeth back his soul from the pit, and his life from perishing by the sword.",
      "plainText" : "He keepeth back his soul from the pit, and his life from perishing by the sword."
    }
    ,
    {
      "type" : "verse",
      "id" : "v19",
      "number" : "19",
      "absolute" : "13670",
      "text" : "He is chastened also with pain upon his bed, and the multitude of his bones with strong <span class='extra'>pain<\/span>:",
      "plainText" : "He is chastened also with pain upon his bed, and the multitude of his bones with strong pain:"
    }
    ,
    {
      "type" : "verse",
      "id" : "v20",
      "number" : "20",
      "absolute" : "13671",
      "text" : "So that his life abhorreth bread, and his soul dainty meat.",
      "plainText" : "So that his life abhorreth bread, and his soul dainty meat."
    }
    ,
    {
      "type" : "verse",
      "id" : "v21",
      "number" : "21",
      "absolute" : "13672",
      "text" : "His flesh is consumed away, that it cannot be seen; and his bones <span class='extra'>that<\/span> were not seen stick out.",
      "plainText" : "His flesh is consumed away, that it cannot be seen; and his bones that were not seen stick out."
    }
    ,
    {
      "type" : "verse",
      "id" : "v22",
      "number" : "22",
      "absolute" : "13673",
      "text" : "Yea, his soul draweth near unto the grave, and his life to the destroyers.",
      "plainText" : "Yea, his soul draweth near unto the grave, and his life to the destroyers."
    }
    ,
    {
      "type" : "verse",
      "id" : "v23",
      "number" : "23",
      "absolute" : "13674",
      "text" : "If there be a messenger with him, an interpreter, one among a thousand, to shew unto man his uprightness:",
      "plainText" : "If there be a messenger with him, an interpreter, one among a thousand, to shew unto man his uprightness:"
    }
    ,
    {
      "type" : "verse",
      "id" : "v24",
      "number" : "24",
      "absolute" : "13675",
      "text" : "Then he is gracious unto him, and saith, Deliver him from going down to the pit: I have found a ransom.",
      "plainText" : "Then he is gracious unto him, and saith, Deliver him from going down to the pit: I have found a ransom."
    }
    ,
    {
      "type" : "verse",
      "id" : "v25",
      "number" : "25",
      "absolute" : "13676",
      "text" : "His flesh shall be fresher than a child's: he shall return to the days of his youth:",
      "plainText" : "His flesh shall be fresher than a child's: he shall return to the days of his youth:"
    }
    ,
    {
      "type" : "verse",
      "id" : "v26",
      "number" : "26",
      "absolute" : "13677",
      "text" : "He shall pray unto God, and he will be favourable unto him: and he shall see his face with joy: for he will render unto man his righteousness.",
      "plainText" : "He shall pray unto God, and he will be favourable unto him: and he shall see his face with joy: for he will render unto man his righteousness."
    }
    ,
    {
      "type" : "verse",
      "id" : "v27",
      "number" : "27",
      "absolute" : "13678",
      "text" : "He looketh upon men, and <span class='extra'>if any<\/span> say, I have sinned, and perverted <span class='extra'>that which was<\/span> right, and it profited me not;",
      "plainText" : "He looketh upon men, and if any say, I have sinned, and perverted that which was right, and it profited me not;"
    }
    ,
    {
      "type" : "verse",
      "id" : "v28",
      "number" : "28",
      "absolute" : "13679",
      "text" : "He will deliver his soul from going into the pit, and his life shall see the light.",
      "plainText" : "He will deliver his soul from going into the pit, and his life shall see the light."
    }
    ,
    {
      "type" : "verse",
      "id" : "v29",
      "number" : "29",
      "absolute" : "13680",
      "text" : "Lo, all these <span class='extra'>things<\/span> worketh God oftentimes with man,",
      "plainText" : "Lo, all these things worketh God oftentimes with man,"
    }
    ,
    {
      "type" : "verse",
      "id" : "v30",
      "number" : "30",
      "absolute" : "13681",
      "text" : "To bring back his soul from the pit, to be enlightened with the light of the living.",
      "plainText" : "To bring back his soul from the pit, to be enlightened with the light of the living."
    }
    ,
    {
      "type" : "verse",
      "id" : "v31",
      "number" : "31",
      "absolute" : "13682",
      "text" : "Mark well, O Job, hearken unto me: hold thy peace, and I will speak.",
      "plainText" : "Mark well, O Job, hearken unto me: hold thy peace, and I will speak."
    }
    ,
    {
      "type" : "verse",
      "id" : "v32",
      "number" : "32",
      "absolute" : "13683",
      "text" : "If thou hast any thing to say, answer me: speak, for I desire to justify thee.",
      "plainText" : "If thou hast any thing to say, answer me: speak, for I desire to justify thee."
    }
    ,
    {
      "type" : "verse",
      "id" : "v33",
      "number" : "33",
      "absolute" : "13684",
      "text" : "If not, hearken unto me: hold thy peace, and I shall teach thee wisdom.",
      "plainText" : "If not, hearken unto me: hold thy peace, and I shall teach thee wisdom."
    }
  ]
}

